{"version": 0.6, "generator": "Overpass API 0.7.62.10 2d4cfc48", "osm3s": {"timestamp_osm_base": "2026-02-08T12:07:16Z", "copyright": "The data included in this document is from www.openstreetmap.org. The data is made available under ODbL."}, "elements": [{"type": "node", "id": 244894316, "lat": 46.8640839, "lon": 11.3089874, "tags": {"aerialway": "station", "name": "Ratschings-Jaufen - Racines-Giovo", "name:de": "Ratschings-Jaufen", "name:it": "Racines-Giovo"}}, {"type": "node", "id": 244894317, "lat": 46.8597186, "lon": 11.3079162, "tags": {"aerialway": "pylon"}}, {"type": "node", "id": 244894318, "lat": 46.8582824, "lon": 11.3075638, "tags": {"aerialway": "pylon"}}, {"type": "node", "id": 244894319, "lat": 46.850361, "lon": 11.3056204, "tags": {"aerialway": "pylon"}}, {"type": "node", "id": 244894320, "lat": 46.847818, "lon": 11.3049965, "tags": {"aerialway": "station", "name": "Ratschings-Jaufen - Racines-Giovo", "name:de": "Ratschings-Jaufen", "name:it": "Racines-Giovo"}}, {"type": "node", "id": 244894329, "lat": 46.8609481, "lon": 11.3018512, "tags": {"aerialway": "station", "name": "Wasserfaller Alm"}}, {"type": "node", "id": 244894330, "lat": 46.8561643, "lon": 11.2998464, "tags": {"aerialway": "pylon"}}, {"type": "node", "id": 244894331, "lat": 46.8510458, "lon": 11.2977016, "tags": {"aerialway": "pylon"}}, {"type": "node", "id": 244894332, "lat": 46.8458877, "lon": 11.2955404, "tags": {"aerialway": "station", "name": "Wasserfaller Alm - Malga Cascata"}}, {"type": "node", "id": 244894345, "lat": 46.8600027, "lon": 11.3028611, "tags": {"aerialway": "station", "name": "Blosegg"}}, {"type": "node", "id": 244894357, "lat": 46.849972, "lon": 11.2949011, "tags": {"aerialway": "station", "name": "Saxner"}}, {"type": "node", "id": 244894359, "lat": 46.8416038, "lon": 11.2844434, "tags": {"aerialway": "station", "name": "Saxner"}}, {"type": "node", "id": 244894379, "lat": 46.8506822, "lon": 11.3214339, "tags": {"aerialway": "station", "name": "Kalcher Alm - Malga Calice", "name:de": "Kalcher Alm", "name:it": "Malga Calice", "source": "https://www.sentres.com/it/andare-in-malga/malga-calice"}}, {"type": "node", "id": 244894381, "lat": 46.8425435, "lon": 11.3219241, "tags": {"aerialway": "yes", "name": "Kalcher Alm - Malga Calice", "name:de": "Kalcher Alm", "name:it": "Malga Calice", "public_transport": "station", "source": "https://www.sentres.com/it/andare-in-malga/malga-calice"}}, {"type": "node", "id": 244894383, "lat": 46.8489078, "lon": 11.3070745, "tags": {"aerialway": "station", "name": "Rinneralm - Malga Rinner", "name:de": "Rinneralm", "name:it": "Malga Rinner"}}, {"type": "node", "id": 244894385, "lat": 46.8403714, "lon": 11.3143833, "tags": {"aerialway": "yes", "name": "Rinneralm - Malga Rinner", "name:de": "Rinneralm", "name:it": "Malga Rinner", "public_transport": "station"}}, {"type": "node", "id": 244894394, "lat": 46.8479164, "lon": 11.3032883, "tags": {"aerialway": "station", "name": "Enzian"}}, {"type": "node", "id": 244898331, "lat": 46.8408147, "lon": 11.3018814, "tags": {"aerialway": "station", "name": "Enzian"}}, {"type": "node", "id": 253776121, "lat": 46.8685276, "lon": 11.0397672, "tags": {"aerialway": "station", "aerialway:access": "both", "aerialway:station": "bottom", "ele": "2345", "name": "Top-Express Obergurgl-Hochgurgl", "public_transport": "station"}}, {"type": "node", "id": 253776122, "lat": 46.8729265, "lon": 11.0429227, "tags": {"aerialway": "pylon", "source": "Bing Maps"}}, {"type": "node", "id": 253776123, "lat": 46.8814946, "lon": 11.0490137, "tags": {"aerialway": "pylon", "source": "Bing Maps"}}, {"type": "node", "id": 253776124, "lat": 46.8862216, "lon": 11.0523745, "tags": {"aerialway": "pylon", "source": "Bing Maps"}}, {"type": "node", "id": 253776125, "lat": 46.8895477, "lon": 11.0547395, "tags": {"aerialway": "pylon", "source": "Bing Maps"}}, {"type": "node", "id": 253776126, "lat": 46.8907969, "lon": 11.0556277, "tags": {"aerialway": "pylon", "source": "Bing Maps"}}, {"type": "node", "id": 253776128, "lat": 46.8977481, "lon": 11.0605708, "tags": {"aerialway": "station", "aerialway:access": "both", "aerialway:station": "top", "ele": "2430", "name": "Top-Express Obergurgl-Hochgurgl", "public_transport": "station"}}, {"type": "node", "id": 253776129, "lat": 46.8981769, "lon": 11.060949, "tags": {"aerialway": "station", "aerialway:station": "bottom", "ele": "2430", "name": "TOP Wurmkogel I", "public_transport": "station"}}, {"type": "node", "id": 253776130, "lat": 46.8977766, "lon": 11.0615454, "tags": {"aerialway": "pylon", "source": "Bing Maps"}}, {"type": "node", "id": 253776131, "lat": 46.8949825, "lon": 11.0652726, "tags": {"aerialway": "pylon", "source": "Bing Maps"}}, {"type": "node", "id": 253776132, "lat": 46.8936315, "lon": 11.0670747, "tags": {"aerialway": "pylon", "source": "Bing Maps"}}, {"type": "node", "id": 253776133, "lat": 46.8921886, "lon": 11.0689994, "tags": {"aerialway": "pylon", "source": "Bing Maps"}}, {"type": "node", "id": 253776134, "lat": 46.8903514, "lon": 11.0714499, "tags": {"aerialway": "pylon", "source": "Bing Maps"}}, {"type": "node", "id": 253776135, "lat": 46.8883003, "lon": 11.0741857, "tags": {"aerialway": "pylon", "source": "Bing Maps"}}, {"type": "node", "id": 253776137, "lat": 46.8846607, "lon": 11.0790398, "tags": {"aerialway": "station", "aerialway:station": "top", "name": "Top Wurmkoglbahn I", "public_transport": "station"}}, {"type": "node", "id": 253776138, "lat": 46.8872611, "lon": 11.0752732, "tags": {"aerialway": "station", "aerialway:access": "entry", "aerialway:station": "bottom", "aerialway:summer:access": "both", "name": "Top Wurmkoglbahn II", "public_transport": "station"}}, {"type": "node", "id": 253776141, "lat": 46.8833579, "lon": 11.0800498, "tags": {"aerialway": "pylon"}}, {"type": "node", "id": 253776143, "lat": 46.8804966, "lon": 11.083551, "tags": {"aerialway": "pylon"}}, {"type": "node", "id": 253776144, "lat": 46.8802783, "lon": 11.0838181, "tags": {"aerialway": "station", "aerialway:access": "exit", "aerialway:station": "top", "aerialway:summer:access": "both", "ele": "3064", "name": "Top Wurmkoglbahn II", "public_transport": "station"}}, {"type": "node", "id": 253776145, "lat": 46.8986386, "lon": 11.0611872, "tags": {"aerialway": "station", "aerialway:station": "bottom", "ele": "2422", "name": "Schemerbahn", "public_transport": "station"}}, {"type": "node", "id": 253776146, "lat": 46.8971255, "lon": 11.0653654, "tags": {"aerialway": "pylon", "source": "Bing Maps"}}, {"type": "node", "id": 253776147, "lat": 46.8955784, "lon": 11.0696372, "tags": {"aerialway": "pylon", "source": "Bing Maps"}}, {"type": "node", "id": 253776148, "lat": 46.8942525, "lon": 11.073298, "tags": {"aerialway": "pylon", "source": "Bing Maps"}}, {"type": "node", "id": 253776149, "lat": 46.8927543, "lon": 11.0774347, "tags": {"aerialway": "pylon", "source": "Bing Maps"}}, {"type": "node", "id": 253776150, "lat": 46.8919524, "lon": 11.0796486, "tags": {"aerialway": "pylon", "source": "Bing Maps"}}, {"type": "node", "id": 253776151, "lat": 46.8907896, "lon": 11.0828592, "tags": {"aerialway": "station", "aerialway:station": "top", "ele": "2922", "name": "Top Schermerbahn 3000", "public_transport": "station"}}, {"type": "node", "id": 253776152, "lat": 46.899712, "lon": 11.0517279, "tags": {"aerialway": "station", "aerialway:access": "entry", "aerialway:station": "bottom", "name": "Gro\u00dfe Karbahn", "public_transport": "station"}}, {"type": "node", "id": 253776154, "lat": 46.8997925, "lon": 11.0601546, "tags": {"aerialway": "pylon", "source": "Bing Maps"}}, {"type": "node", "id": 253776167, "lat": 46.866766, "lon": 11.0390176, "tags": {"aerialway": "pylon", "source": "Bing Maps"}}, {"type": "node", "id": 253776168, "lat": 46.8654143, "lon": 11.0399143, "tags": {"aerialway": "pylon", "source": "Bing Maps"}}, {"type": "node", "id": 253776169, "lat": 46.8625586, "lon": 11.0418087, "tags": {"aerialway": "pylon", "source": "Bing Maps"}}, {"type": "node", "id": 253776170, "lat": 46.860991, "lon": 11.0428486, "tags": {"aerialway": "pylon", "source": "Bing Maps"}}, {"type": "node", "id": 253776171, "lat": 46.859567, "lon": 11.0437931, "tags": {"aerialway": "pylon", "source": "Bing Maps"}}, {"type": "node", "id": 253776172, "lat": 46.8588284, "lon": 11.0442954, "tags": {"aerialway": "station", "aerialway:access": "exit", "aerialway:station": "top", "name": "Festkoglbahn", "public_transport": "station"}}, {"type": "node", "id": 253776177, "lat": 46.8695132, "lon": 11.0268865, "tags": {"aerialway": "station", "aerialway:access": "entry", "aerialway:station": "mid", "ele": "1930", "name": "Ro\u00dfkarbahn", "public_transport": "station", "wheelchair": "limited"}}, {"type": "node", "id": 253776179, "lat": 46.866931, "lon": 11.0311831, "tags": {"aerialway": "pylon", "source": "Bing Maps"}}, {"type": "node", "id": 253776180, "lat": 46.8655739, "lon": 11.0334412, "tags": {"aerialway": "station", "aerialway:access": "entry", "aerialway:station": "mid", "ele": "2260", "name": "Ro\u00dfkarbahn Mittelstation", "public_transport": "station"}}, {"type": "node", "id": 253776181, "lat": 46.8634078, "lon": 11.0368994, "tags": {"aerialway": "pylon", "source": "Bing Maps"}}, {"type": "node", "id": 253776186, "lat": 46.8595313, "lon": 11.0284704, "tags": {"aerialway": "station", "aerialway:access": "entry", "aerialway:station": "bottom", "name": "Plattachbahn", "public_transport": "station"}}, {"type": "node", "id": 253776187, "lat": 46.8590673, "lon": 11.0326019, "tags": {"aerialway": "pylon", "source": "Bing Maps"}}, {"type": "node", "id": 253776189, "lat": 46.8583585, "lon": 11.0389125, "tags": {"aerialway": "station", "aerialway:access": "both", "aerialway:station": "top", "name": "Plattachbahn Mittelstation", "public_transport": "station"}}, {"type": "node", "id": 253776191, "lat": 46.8576518, "lon": 11.0413127, "tags": {"aerialway": "pylon", "source": "Bing Maps"}}, {"type": "node", "id": 253776195, "lat": 46.8551976, "lon": 11.049648, "tags": {"aerialway": "station", "aerialway:access": "exit", "aerialway:station": "top", "name": "Plattachbahn", "public_transport": "station"}}, {"type": "node", "id": 253776196, "lat": 46.8692214, "lon": 11.026964, "tags": {"aerialway": "station", "aerialway:access": "both", "aerialway:station": "mid", "aerialway:summer:access": "both", "ele": "1930", "name": "Hohe Mut Bahn", "public_transport": "station"}}, {"type": "node", "id": 253776204, "lat": 46.8602988, "lon": 11.0228534, "tags": {"aerialway": "station", "aerialway:access": "both", "aerialway:station": "mid", "aerialway:summer:access": "both", "ele": "2067", "name": "Hohe Mut Bahn Mittelstation", "public_transport": "station"}}, {"type": "node", "id": 253776210, "lat": 46.8488475, "lon": 11.0288885, "tags": {"aerialway": "station", "aerialway:access": "both", "aerialway:station": "top", "aerialway:summer:access": "both", "ele": "2642", "name": "Hohe Mut Bahn", "public_transport": "station"}}, {"type": "node", "id": 253776211, "lat": 46.8602225, "lon": 11.0207047, "tags": {"aerialway": "station", "aerialway:access": "entry", "aerialway:station": "bottom", "name": "Bruggenbodenbahn", "public_transport": "station"}}, {"type": "node", "id": 253776218, "lat": 46.8549498, "lon": 11.0206826, "tags": {"aerialway": "station", "aerialway:access": "exit", "aerialway:station": "top", "name": "Steinmannbahn", "public_transport": "station"}}, {"type": "node", "id": 295318451, "lat": 46.8602022, "lon": 10.9150049, "tags": {"aerialway": "station", "aerialway:access": "entry", "aerialway:station": "bottom", "aerialway:summer:access": "both", "name": "Wildspitze", "public_transport": "station", "wheelchair": "no"}}, {"type": "node", "id": 313310535, "lat": 46.9229509, "lon": 10.9447766, "tags": {"aerialway": "station", "aerialway:access": "entry", "aerialway:station": "bottom", "aerialway:summer:access": "both", "public_transport": "station", "wheelchair": "limited", "wheelchair:description": "Kabinenbahn mit normaler Eiinstiegsbreite"}}, {"type": "node", "id": 313310536, "lat": 46.9205866, "lon": 10.9185388, "tags": {"aerialway": "station", "aerialway:access": "both", "aerialway:station": "top", "aerialway:summer:access": "both", "ele": "3244", "public_transport": "station", "source:ele": "\u00d6K50;Laserscan"}}, {"type": "node", "id": 313310539, "lat": 46.9234195, "lon": 10.9452682, "tags": {"aerialway": "station", "aerialway:access": "entry", "aerialway:station": "bottom", "public_transport": "station", "wheelchair": "no"}}, {"type": "node", "id": 313310540, "lat": 46.929891, "lon": 10.9384355, "tags": {"aerialway": "station", "aerialway:access": "exit", "aerialway:station": "top", "public_transport": "station"}}, {"type": "node", "id": 313310543, "lat": 46.9258642, "lon": 10.9295067, "tags": {"aerialway": "station", "aerialway:access": "both", "aerialway:station": "top", "aerialway:summer:access": "both", "ele": "3243", "name": "Schwarze Schneid", "public_transport": "station", "source:ele": "\u00d6K50;Laserscan"}}, {"type": "node", "id": 340106298, "lat": 46.8866978, "lon": 11.0737868, "tags": {"aerialway": "station", "aerialway:access": "both", "aerialway:station": "top", "aerialway:summer:access": "both", "name": "Hochgurglbahn", "public_transport": "station"}}, {"type": "node", "id": 340106299, "lat": 46.8992251, "lon": 11.0519482, "tags": {"aerialway": "station", "aerialway:access": "both", "aerialway:station": "mid", "aerialway:summer:access": "both", "ele": "2160", "name": "Hochgurglbahn Mittelstation", "public_transport": "station"}}, {"type": "node", "id": 340106300, "lat": 46.8978013, "lon": 11.0407442, "tags": {"aerialway": "station", "aerialway:access": "both", "aerialway:station": "bottom", "aerialway:summer:access": "both", "ele": "1789", "name": "Hochgurglbahn", "public_transport": "station"}}, {"type": "node", "id": 341999459, "lat": 46.939513, "lon": 11.0029704, "tags": {"aerialway": "station", "aerialway:access": "entry", "aerialway:station": "bottom", "public_transport": "station"}}, {"type": "node", "id": 447031896, "lat": 46.904197, "lon": 11.42965, "tags": {"aerialway": "station", "aerialway:access": "both", "aerialway:summer:access": "both", "name": "Rosskopf", "public_transport": "station"}}, {"type": "node", "id": 540378274, "lat": 46.9405915, "lon": 11.3744608, "tags": {"aerialway": "station", "aerialway:access": "both", "aerialway:summer:access": "both", "name": "Bergstation Ladurns - Stazione a monte Ladurns", "name:de": "Bergstation Ladurns", "name:it": "Stazione a monte Ladurns", "operator": "Bergbahnen Ladurns GmbH", "public_transport": "station"}}, {"type": "node", "id": 540378278, "lat": 46.9511417, "lon": 11.3880478, "tags": {"aerialway": "station", "aerialway:access": "both", "aerialway:summer:access": "both", "name": "Ladurns I", "name:de": "Bergbahnen Ladurns Gossensass", "public_transport": "station"}}, {"type": "node", "id": 669878652, "lat": 46.926293, "lon": 10.9292564, "tags": {"aerialway": "pylon"}}, {"type": "node", "id": 669878657, "lat": 46.9326041, "lon": 10.9256041, "tags": {"aerialway": "pylon"}}, {"type": "node", "id": 677810074, "lat": 46.7918018, "lon": 11.0989719, "tags": {"aerialway": "station", "ele": "1964", "name": "Karjoch Express", "public_transport": "station"}}, {"type": "node", "id": 737414842, "lat": 46.9178021, "lon": 11.3955763, "tags": {"aerialway": "station", "name": "Stock", "source": "foreign trace from OSM"}}, {"type": "node", "id": 737415765, "lat": 46.9111504, "lon": 11.4101618, "tags": {"aerialway": "station", "name": "Stock", "source": "foreign trace from OSM"}}, {"type": "node", "id": 1066292519, "lat": 46.8909541, "lon": 11.0824051, "tags": {"aerialway": "pylon", "source": "Bing Maps"}}, {"type": "node", "id": 1066292545, "lat": 46.8941534, "lon": 11.0580145, "tags": {"aerialway": "pylon", "source": "Bing Maps"}}, {"type": "node", "id": 1066292551, "lat": 46.8591462, "lon": 11.0437025, "tags": {"aerialway": "pylon", "source": "Bing Maps"}}, {"type": "node", "id": 1066292565, "lat": 46.8670053, "lon": 11.0310595, "tags": {"aerialway": "pylon", "source": "Bing Maps"}}, {"type": "node", "id": 1066292585, "lat": 46.8919711, "lon": 11.0645947, "tags": {"aerialway": "pylon", "source": "Bing Maps"}}, {"type": "node", "id": 1066292595, "lat": 46.8584736, "lon": 11.0378876, "tags": {"aerialway": "pylon", "source": "Bing Maps"}}, {"type": "node", "id": 1066292633, "lat": 46.8684514, "lon": 11.0378995, "tags": {"aerialway": "pylon", "source": "Bing Maps"}}, {"type": "node", "id": 1066292655, "lat": 46.8650717, "lon": 11.0342429, "tags": {"aerialway": "pylon", "source": "Bing Maps"}}, {"type": "node", "id": 1066292694, "lat": 46.8860848, "lon": 11.0771405, "tags": {"aerialway": "pylon", "source": "Bing Maps"}}, {"type": "node", "id": 1066292720, "lat": 46.8959791, "lon": 11.0576073, "tags": {"aerialway": "pylon", "source": "Bing Maps"}}, {"type": "node", "id": 1066292757, "lat": 46.8751306, "lon": 11.0444895, "tags": {"aerialway": "pylon", "source": "Bing Maps"}}, {"type": "node", "id": 1066292759, "lat": 46.8962824, "lon": 11.0635386, "tags": {"aerialway": "pylon", "source": "Bing Maps"}}, {"type": "node", "id": 1066292762, "lat": 46.8676769, "lon": 11.0299421, "tags": {"aerialway": "pylon", "source": "Bing Maps"}}, {"type": "node", "id": 1066292765, "lat": 46.8898561, "lon": 11.0682814, "tags": {"aerialway": "pylon", "source": "Bing Maps"}}, {"type": "node", "id": 1066292774, "lat": 46.8585746, "lon": 11.0369888, "tags": {"aerialway": "pylon", "source": "Bing Maps"}}, {"type": "node", "id": 1066292783, "lat": 46.8997198, "lon": 11.0525475, "tags": {"aerialway": "pylon", "source": "Bing Maps"}}, {"type": "node", "id": 1066292802, "lat": 46.8566998, "lon": 11.044546, "tags": {"aerialway": "pylon", "source": "Bing Maps"}}, {"type": "node", "id": 1066292818, "lat": 46.8960095, "lon": 11.0684467, "tags": {"aerialway": "pylon", "source": "Bing Maps"}}, {"type": "node", "id": 1066292822, "lat": 46.8687225, "lon": 11.0377196, "tags": {"aerialway": "pylon", "source": "Bing Maps"}}, {"type": "node", "id": 1066292823, "lat": 46.8900033, "lon": 11.0680249, "tags": {"aerialway": "pylon", "source": "Bing Maps"}}, {"type": "node", "id": 1066292845, "lat": 46.8998355, "lon": 11.0646548, "tags": {"aerialway": "pylon", "source": "Bing Maps"}}, {"type": "node", "id": 1066292850, "lat": 46.8596772, "lon": 11.0428549, "tags": {"aerialway": "pylon", "source": "Bing Maps"}}, {"type": "node", "id": 1066292875, "lat": 46.8658703, "lon": 11.0329479, "tags": {"aerialway": "pylon", "source": "Bing Maps"}}, {"type": "node", "id": 1066292883, "lat": 46.8997712, "lon": 11.0579197, "tags": {"aerialway": "pylon", "source": "Bing Maps"}}, {"type": "node", "id": 1066292890, "lat": 46.8966319, "lon": 11.0630725, "tags": {"aerialway": "pylon", "source": "Bing Maps"}}, {"type": "node", "id": 1066292918, "lat": 46.8581037, "lon": 11.0397781, "tags": {"aerialway": "pylon", "source": "Bing Maps"}}, {"type": "node", "id": 1066292926, "lat": 46.8997528, "lon": 11.0560009, "tags": {"aerialway": "pylon", "source": "Bing Maps"}}, {"type": "node", "id": 1066292936, "lat": 46.8934902, "lon": 11.0754029, "tags": {"aerialway": "pylon", "source": "Bing Maps"}}, {"type": "node", "id": 1066292941, "lat": 46.8631069, "lon": 11.041445, "tags": {"aerialway": "pylon", "source": "Bing Maps"}}, {"type": "node", "id": 1066292948, "lat": 46.887972, "lon": 11.0715657, "tags": {"aerialway": "pylon", "source": "Bing Maps"}}, {"type": "node", "id": 1066292962, "lat": 46.8584404, "lon": 11.0381835, "tags": {"aerialway": "pylon", "source": "Bing Maps"}}, {"type": "node", "id": 1066292995, "lat": 46.8951861, "lon": 11.0707202, "tags": {"aerialway": "pylon", "source": "Bing Maps"}}, {"type": "node", "id": 1066292997, "lat": 46.8646946, "lon": 11.0403917, "tags": {"aerialway": "pylon", "source": "Bing Maps"}}, {"type": "node", "id": 1066293022, "lat": 46.8592112, "lon": 11.0313208, "tags": {"aerialway": "pylon", "source": "Bing Maps"}}, {"type": "node", "id": 1066293052, "lat": 46.8919001, "lon": 11.0693842, "tags": {"aerialway": "pylon", "source": "Bing Maps"}}, {"type": "node", "id": 1066293057, "lat": 46.8610928, "lon": 11.0405951, "tags": {"aerialway": "pylon", "source": "Bing Maps"}}, {"type": "node", "id": 1066293082, "lat": 46.872144, "lon": 11.0354496, "tags": {"aerialway": "pylon", "source": "Bing Maps"}}, {"type": "node", "id": 1066293093, "lat": 46.85613, "lon": 11.0464813, "tags": {"aerialway": "pylon", "source": "Bing Maps"}}, {"type": "node", "id": 1066293118, "lat": 46.8739604, "lon": 11.0342445, "tags": {"aerialway": "pylon", "source": "Bing Maps"}}, {"type": "node", "id": 1066293135, "lat": 46.8946856, "lon": 11.0656686, "tags": {"aerialway": "pylon", "source": "Bing Maps"}}, {"type": "node", "id": 1066293139, "lat": 46.8885866, "lon": 11.0704944, "tags": {"aerialway": "pylon", "source": "Bing Maps"}}, {"type": "node", "id": 1066293157, "lat": 46.8757183, "lon": 11.0330781, "tags": {"aerialway": "station", "aerialway:access": "entry", "aerialway:station": "bottom", "name": "Festkoglbahn", "public_transport": "station"}}, {"type": "node", "id": 1066293158, "lat": 46.8570394, "lon": 11.0433927, "tags": {"aerialway": "pylon", "source": "Bing Maps"}}, {"type": "node", "id": 1066293166, "lat": 46.8658045, "lon": 11.0330575, "tags": {"aerialway": "pylon", "source": "Bing Maps"}}, {"type": "node", "id": 1066293175, "lat": 46.8935764, "lon": 11.061796, "tags": {"aerialway": "pylon", "source": "Bing Maps"}}, {"type": "node", "id": 1066293185, "lat": 46.8593939, "lon": 11.0296941, "tags": {"aerialway": "pylon", "source": "Bing Maps"}}, {"type": "node", "id": 1066293188, "lat": 46.8974215, "lon": 11.0603385, "tags": {"aerialway": "pylon", "source": "Bing Maps"}}, {"type": "node", "id": 1066293210, "lat": 46.862191, "lon": 11.0388419, "tags": {"aerialway": "pylon", "source": "Bing Maps"}}, {"type": "node", "id": 1066293228, "lat": 46.8673351, "lon": 11.0305107, "tags": {"aerialway": "pylon", "source": "Bing Maps"}}, {"type": "node", "id": 1066293236, "lat": 46.8864046, "lon": 11.076714, "tags": {"aerialway": "pylon", "source": "Bing Maps"}}, {"type": "node", "id": 1066293274, "lat": 46.8975605, "lon": 11.0548504, "tags": {"aerialway": "pylon", "source": "Bing Maps"}}, {"type": "node", "id": 1066293285, "lat": 46.899726, "lon": 11.0531886, "tags": {"aerialway": "pylon", "source": "Bing Maps"}}, {"type": "node", "id": 1066293303, "lat": 46.8592159, "lon": 11.044026, "tags": {"aerialway": "pylon", "source": "Bing Maps"}}, {"type": "node", "id": 1066293306, "lat": 46.8689102, "lon": 11.0278898, "tags": {"aerialway": "pylon", "source": "Bing Maps"}}, {"type": "node", "id": 1066293312, "lat": 46.8871283, "lon": 11.0730363, "tags": {"aerialway": "pylon", "source": "Bing Maps"}}, {"type": "node", "id": 1066293331, "lat": 46.8587618, "lon": 11.0353222, "tags": {"aerialway": "pylon", "source": "Bing Maps"}}, {"type": "node", "id": 1066293393, "lat": 46.8694485, "lon": 11.037238, "tags": {"aerialway": "pylon", "source": "Bing Maps"}}, {"type": "node", "id": 1066293396, "lat": 46.8692466, "lon": 11.02733, "tags": {"aerialway": "pylon", "source": "Bing Maps"}}, {"type": "node", "id": 1066293401, "lat": 46.8909303, "lon": 11.066409, "tags": {"aerialway": "pylon", "source": "Bing Maps"}}, {"type": "node", "id": 1066293420, "lat": 46.8589013, "lon": 11.03408, "tags": {"aerialway": "pylon", "source": "Bing Maps"}}, {"type": "node", "id": 1066293439, "lat": 46.888923, "lon": 11.0733551, "tags": {"aerialway": "pylon", "source": "Bing Maps"}}, {"type": "node", "id": 1066293457, "lat": 46.8977444, "lon": 11.0636563, "tags": {"aerialway": "pylon", "source": "Bing Maps"}}, {"type": "node", "id": 1066293460, "lat": 46.870809, "lon": 11.0363353, "tags": {"aerialway": "pylon", "source": "Bing Maps"}}, {"type": "node", "id": 1066293487, "lat": 46.8988564, "lon": 11.052591, "tags": {"aerialway": "pylon", "source": "Bing Maps"}}, {"type": "node", "id": 1066293488, "lat": 46.8555877, "lon": 11.048323, "tags": {"aerialway": "pylon", "source": "Bing Maps"}}, {"type": "node", "id": 1066293519, "lat": 46.8751527, "lon": 11.0334534, "tags": {"aerialway": "pylon", "source": "Bing Maps"}}, {"type": "node", "id": 1066293532, "lat": 46.8584211, "lon": 11.0383558, "tags": {"aerialway": "pylon", "source": "Bing Maps"}}, {"type": "node", "id": 1066293535, "lat": 46.8643379, "lon": 11.0354145, "tags": {"aerialway": "pylon", "source": "Bing Maps"}}, {"type": "node", "id": 1071613608, "lat": 46.8606595, "lon": 11.0177342, "tags": {"aerialway": "pylon"}}, {"type": "node", "id": 1071613624, "lat": 46.8754621, "lon": 11.0332481, "tags": {"aerialway": "pylon", "source": "Bing Maps"}}, {"type": "node", "id": 1071613653, "lat": 46.8575445, "lon": 11.021225, "tags": {"aerialway": "pylon"}}, {"type": "node", "id": 1071613743, "lat": 46.8613962, "lon": 11.0173516, "tags": {"aerialway": "station", "aerialway:access": "entry", "aerialway:station": "bottom", "name": "Steinmannbahn", "public_transport": "station"}}, {"type": "node", "id": 1071613852, "lat": 46.8689241, "lon": 11.0400602, "tags": {"aerialway": "pylon"}}, {"type": "node", "id": 1071613878, "lat": 46.8599472, "lon": 11.0207582, "tags": {"aerialway": "pylon"}}, {"type": "node", "id": 1071613912, "lat": 46.8596031, "lon": 11.0182827, "tags": {"aerialway": "pylon"}}, {"type": "node", "id": 1071613978, "lat": 46.8567176, "lon": 11.0197811, "tags": {"aerialway": "pylon"}}, {"type": "node", "id": 1071614013, "lat": 46.8553215, "lon": 11.0492271, "tags": {"aerialway": "pylon"}}, {"type": "node", "id": 1071614043, "lat": 46.8554874, "lon": 11.0253893, "tags": {"aerialway": "pylon"}}, {"type": "node", "id": 1071614075, "lat": 46.8553075, "lon": 11.0205133, "tags": {"aerialway": "pylon"}}, {"type": "node", "id": 1071614093, "lat": 46.8592228, "lon": 11.0208989, "tags": {"aerialway": "pylon"}}, {"type": "node", "id": 1071614104, "lat": 46.858016, "lon": 11.0191069, "tags": {"aerialway": "pylon"}}, {"type": "node", "id": 1071614173, "lat": 46.858265, "lon": 11.021085, "tags": {"aerialway": "pylon"}}, {"type": "node", "id": 1071640770, "lat": 46.8849224, "lon": 11.0786941, "tags": {"aerialway": "pylon", "source": "Bing Maps"}}, {"type": "node", "id": 1071640785, "lat": 46.8998149, "lon": 11.0624996, "tags": {"aerialway": "pylon", "source": "Bing Maps"}}, {"type": "node", "id": 1071640824, "lat": 46.8866117, "lon": 11.0760679, "tags": {"aerialway": "pylon", "source": "Bing Maps"}}, {"type": "node", "id": 1071640829, "lat": 46.8825204, "lon": 11.0810746, "tags": {"aerialway": "pylon"}}, {"type": "node", "id": 1071640838, "lat": 46.8983734, "lon": 11.0619196, "tags": {"aerialway": "pylon", "source": "Bing Maps"}}, {"type": "node", "id": 1071640928, "lat": 46.8861011, "lon": 11.0766928, "tags": {"aerialway": "pylon", "source": "Bing Maps"}}, {"type": "node", "id": 1071640995, "lat": 46.8870715, "lon": 11.0755053, "tags": {"aerialway": "pylon", "source": "Bing Maps"}}, {"type": "node", "id": 1071641047, "lat": 46.8849186, "lon": 11.0781399, "tags": {"aerialway": "pylon", "source": "Bing Maps"}}, {"type": "node", "id": 1071641070, "lat": 46.8998113, "lon": 11.0621247, "tags": {"aerialway": "pylon", "source": "Bing Maps"}}, {"type": "node", "id": 1071641147, "lat": 46.8863148, "lon": 11.0764313, "tags": {"aerialway": "pylon", "source": "Bing Maps"}}, {"type": "node", "id": 1079431722, "lat": 46.8983027, "lon": 11.0446895, "tags": {"aerialway": "pylon"}}, {"type": "node", "id": 1079431769, "lat": 46.8985939, "lon": 11.0469812, "tags": {"aerialway": "pylon"}}, {"type": "node", "id": 1083602580, "lat": 46.8606194, "lon": 10.9137848, "tags": {"aerialway": "pylon"}}, {"type": "node", "id": 1083602611, "lat": 46.8606763, "lon": 10.9136183, "tags": {"aerialway": "pylon", "ref": "3"}}, {"type": "node", "id": 1086985557, "lat": 46.8571644, "lon": 11.0245055, "tags": {"aerialway": "pylon"}}, {"type": "node", "id": 1086985561, "lat": 46.849435, "lon": 11.0285789, "tags": {"aerialway": "pylon"}}, {"type": "node", "id": 1086985568, "lat": 46.858425, "lon": 11.0238411, "tags": {"aerialway": "pylon"}}, {"type": "node", "id": 1086985575, "lat": 46.8594867, "lon": 11.0232815, "tags": {"aerialway": "pylon"}}, {"type": "node", "id": 1086985590, "lat": 46.8500438, "lon": 11.0282581, "tags": {"aerialway": "pylon"}}, {"type": "node", "id": 1086985592, "lat": 46.8599455, "lon": 11.0230397, "tags": {"aerialway": "pylon"}}, {"type": "node", "id": 1086985595, "lat": 46.8579497, "lon": 11.0240916, "tags": {"aerialway": "pylon"}}, {"type": "node", "id": 1086985597, "lat": 46.8542193, "lon": 11.0260576, "tags": {"aerialway": "pylon"}}, {"type": "node", "id": 1086985599, "lat": 46.8576118, "lon": 11.0242697, "tags": {"aerialway": "pylon"}}, {"type": "node", "id": 1086985609, "lat": 46.8518148, "lon": 11.0273248, "tags": {"aerialway": "pylon"}}, {"type": "node", "id": 1086985612, "lat": 46.8525948, "lon": 11.0269138, "tags": {"aerialway": "pylon"}}, {"type": "node", "id": 1086985615, "lat": 46.8507417, "lon": 11.0278903, "tags": {"aerialway": "pylon"}}, {"type": "node", "id": 1103629491, "lat": 46.8998396, "lon": 11.0650792, "tags": {"aerialway": "station", "aerialway:access": "exit", "aerialway:station": "top", "aerialway:summer:access": "no", "ele": "2538", "name": "Gro\u00dfe Karbahn", "public_transport": "station"}}, {"type": "node", "id": 1554120762, "lat": 46.8638776, "lon": 10.9042544}, {"type": "node", "id": 1618130726, "lat": 46.8978352, "lon": 11.0410108, "tags": {"aerialway": "pylon"}}, {"type": "node", "id": 1618130747, "lat": 46.8980224, "lon": 11.0424838, "tags": {"aerialway": "pylon"}}, {"type": "node", "id": 1618130754, "lat": 46.8986474, "lon": 11.0474018, "tags": {"aerialway": "pylon"}}, {"type": "node", "id": 1618130767, "lat": 46.8991402, "lon": 11.0512799, "tags": {"aerialway": "pylon"}}, {"type": "node", "id": 1618152016, "lat": 46.8985061, "lon": 11.061553, "tags": {"aerialway": "pylon"}}, {"type": "node", "id": 1618194641, "lat": 46.8974984, "lon": 11.0619165}, {"type": "node", "id": 1667413113, "lat": 46.9039652, "lon": 11.0712125, "tags": {"aerialway": "station", "aerialway:access": "exit", "aerialway:station": "mid", "aerialway:summer:access": "both", "name": "Kirchenkarbahn Mittelstation", "public_transport": "station", "wikidata": "Q62850468", "wikipedia": "de:Kirchenkarbahn II"}}, {"type": "node", "id": 2178445703, "lat": 46.8644259, "lon": 11.3073959, "tags": {"aerialway": "station", "name": "Blosegg"}}, {"type": "node", "id": 2458659523, "lat": 46.9411834, "lon": 10.9971218, "tags": {"aerialway": "pylon"}}, {"type": "node", "id": 2458659533, "lat": 46.9414892, "lon": 10.9960508, "tags": {"aerialway": "pylon"}}, {"type": "node", "id": 2458659541, "lat": 46.94167, "lon": 10.9954178, "tags": {"aerialway": "pylon"}}, {"type": "node", "id": 2458659552, "lat": 46.9419225, "lon": 10.9945338, "tags": {"aerialway": "pylon"}}, {"type": "node", "id": 3226930331, "lat": 46.9206426, "lon": 10.9191605, "tags": {"aerialway": "pylon"}}, {"type": "node", "id": 3226930332, "lat": 46.9213546, "lon": 10.9270617, "tags": {"aerialway": "pylon"}}, {"type": "node", "id": 3226930333, "lat": 46.9214055, "lon": 10.9276265, "tags": {"aerialway": "pylon"}}, {"type": "node", "id": 3226930334, "lat": 46.921712, "lon": 10.931028, "tags": {"aerialway": "pylon"}}, {"type": "node", "id": 3226930335, "lat": 46.9217788, "lon": 10.931769, "tags": {"aerialway": "pylon"}}, {"type": "node", "id": 3226930336, "lat": 46.9221224, "lon": 10.9355826, "tags": {"aerialway": "pylon"}}, {"type": "node", "id": 3226930337, "lat": 46.9225139, "lon": 10.9399274, "tags": {"aerialway": "pylon"}}, {"type": "node", "id": 3226930338, "lat": 46.9227823, "lon": 10.9429056, "tags": {"aerialway": "pylon"}}, {"type": "node", "id": 3226930339, "lat": 46.9228339, "lon": 10.9434786, "tags": {"aerialway": "pylon"}}, {"type": "node", "id": 3226931300, "lat": 46.9241071, "lon": 10.9445422, "tags": {"aerialway": "pylon"}}, {"type": "node", "id": 3226931301, "lat": 46.9251707, "lon": 10.9434193, "tags": {"aerialway": "pylon"}}, {"type": "node", "id": 3226931302, "lat": 46.9257295, "lon": 10.9428293, "tags": {"aerialway": "pylon"}}, {"type": "node", "id": 3226931303, "lat": 46.9266799, "lon": 10.9418259, "tags": {"aerialway": "pylon"}}, {"type": "node", "id": 3226931304, "lat": 46.9277244, "lon": 10.9407231, "tags": {"aerialway": "pylon"}}, {"type": "node", "id": 3226931305, "lat": 46.9287172, "lon": 10.9396748, "tags": {"aerialway": "pylon"}}, {"type": "node", "id": 3226931306, "lat": 46.9295961, "lon": 10.9387469, "tags": {"aerialway": "pylon"}}, {"type": "node", "id": 3229720256, "lat": 46.9344488, "lon": 10.9245759, "tags": {"aerialway": "station", "aerialway:access": "both", "aerialway:station": "mid", "aerialway:summer:access": "both", "name": "Schwarze Schneid Mittelstation", "public_transport": "station"}}, {"type": "node", "id": 3239032538, "lat": 46.9449525, "lon": 10.9839238, "tags": {"aerialway": "station", "aerialway:access": "exit", "aerialway:station": "top", "public_transport": "station"}}, {"type": "node", "id": 3545808258, "lat": 46.909281, "lon": 11.0532899, "tags": {"aerialway": "station", "aerialway:access": "entry", "aerialway:station": "bottom", "aerialway:summer:access": "both", "name": "Kirchenkarbahn I", "public_transport": "station", "wikidata": "Q62850457", "wikipedia": "de:Kirchenkarbahn I"}}, {"type": "node", "id": 3545826061, "lat": 46.8572238, "lon": 11.0212873, "tags": {"aerialway": "station", "aerialway:access": "exit", "aerialway:station": "top", "name": "Bruggenbodenbahn", "public_transport": "station"}}, {"type": "node", "id": 3836944824, "lat": 46.8582609, "lon": 11.0392441, "tags": {"aerialway": "pylon"}}, {"type": "node", "id": 3925544912, "lat": 46.8627087, "lon": 10.9076735, "tags": {"aerialway": "pylon"}}, {"type": "node", "id": 3925544925, "lat": 46.8615042, "lon": 10.9111966, "tags": {"aerialway": "pylon"}}, {"type": "node", "id": 3925544935, "lat": 46.8623332, "lon": 10.908772, "tags": {"aerialway": "pylon"}}, {"type": "node", "id": 3925544941, "lat": 46.8612548, "lon": 10.9119261, "tags": {"aerialway": "pylon"}}, {"type": "node", "id": 3925544944, "lat": 46.8633864, "lon": 10.9056912, "tags": {"aerialway": "pylon"}}, {"type": "node", "id": 4109928652, "lat": 46.935939, "lon": 11.3658148, "tags": {"aerialway": "station", "aerialway:access": "exit", "name": "Wastenegg", "public_transport": "station"}}, {"type": "node", "id": 4823568017, "lat": 46.9098641, "lon": 11.4086293, "tags": {"aerialway": "pylon"}}, {"type": "node", "id": 4823568019, "lat": 46.9125844, "lon": 11.398538, "tags": {"aerialway": "pylon"}}, {"type": "node", "id": 4823568020, "lat": 46.9092071, "lon": 11.4110662, "tags": {"aerialway": "pylon"}}, {"type": "node", "id": 4823572422, "lat": 46.9113719, "lon": 11.4030361, "tags": {"aerialway": "pylon"}}, {"type": "node", "id": 4823572426, "lat": 46.9055454, "lon": 11.4246486, "tags": {"aerialway": "pylon"}}, {"type": "node", "id": 4823572427, "lat": 46.9068812, "lon": 11.4196833, "tags": {"aerialway": "pylon"}}, {"type": "node", "id": 4823572428, "lat": 46.9043099, "lon": 11.4292433, "tags": {"aerialway": "pylon"}}, {"type": "node", "id": 4823572429, "lat": 46.9063909, "lon": 11.4215312, "tags": {"aerialway": "pylon"}}, {"type": "node", "id": 4823572431, "lat": 46.9117338, "lon": 11.4016935, "tags": {"aerialway": "pylon"}}, {"type": "node", "id": 4823572432, "lat": 46.9080344, "lon": 11.4154039, "tags": {"aerialway": "pylon"}}, {"type": "node", "id": 4823572433, "lat": 46.9125616, "lon": 11.3986227, "tags": {"aerialway": "pylon"}}, {"type": "node", "id": 4823572436, "lat": 46.9047412, "lon": 11.4276314, "tags": {"aerialway": "pylon"}}, {"type": "node", "id": 4823572437, "lat": 46.9108476, "lon": 11.4049807, "tags": {"aerialway": "pylon"}}, {"type": "node", "id": 4823572438, "lat": 46.9081988, "lon": 11.4148065, "tags": {"aerialway": "pylon"}}, {"type": "node", "id": 4973565015, "lat": 46.8638053, "lon": 10.9044659, "tags": {"aerialway": "station", "aerialway:access": "exit", "aerialway:station": "top", "aerialway:summer:access": "both", "image": "http://www.flickr.com/photos/yumekosan/8156969749/", "name": "Wildspitze"}}, {"type": "node", "id": 5065053625, "lat": 46.9448167, "lon": 10.9843994, "tags": {"aerialway": "pylon"}}, {"type": "node", "id": 5065053626, "lat": 46.9446382, "lon": 10.9850244, "tags": {"aerialway": "pylon"}}, {"type": "node", "id": 5065053627, "lat": 46.9442935, "lon": 10.9862313, "tags": {"aerialway": "pylon"}}, {"type": "node", "id": 5065053628, "lat": 46.9440457, "lon": 10.987099, "tags": {"aerialway": "pylon"}}, {"type": "node", "id": 5065053629, "lat": 46.94358, "lon": 10.98873, "tags": {"aerialway": "pylon"}}, {"type": "node", "id": 5065053630, "lat": 46.9434689, "lon": 10.9891188, "tags": {"aerialway": "pylon"}}, {"type": "node", "id": 5065053631, "lat": 46.9429083, "lon": 10.991082, "tags": {"aerialway": "pylon"}}, {"type": "node", "id": 5065053632, "lat": 46.9427493, "lon": 10.9916387, "tags": {"aerialway": "pylon"}}, {"type": "node", "id": 5065053633, "lat": 46.942462, "lon": 10.9926447, "tags": {"aerialway": "pylon"}}, {"type": "node", "id": 5420295581, "lat": 46.8500999, "lon": 11.2973053, "tags": {"aerialway": "pylon"}}, {"type": "node", "id": 5420295582, "lat": 46.8492359, "lon": 11.2969432, "tags": {"aerialway": "pylon"}}, {"type": "node", "id": 5420295583, "lat": 46.8607947, "lon": 11.3036731, "tags": {"aerialway": "pylon"}}, {"type": "node", "id": 5420295584, "lat": 46.8425903, "lon": 11.3124836, "tags": {"aerialway": "pylon"}}, {"type": "node", "id": 5420295585, "lat": 46.8472389, "lon": 11.2961065, "tags": {"aerialway": "pylon"}}, {"type": "node", "id": 5420295586, "lat": 46.8465863, "lon": 11.2906698, "tags": {"aerialway": "pylon"}}, {"type": "node", "id": 5420295587, "lat": 46.8418835, "lon": 11.3020931, "tags": {"aerialway": "pylon"}}, {"type": "node", "id": 5420295588, "lat": 46.8491705, "lon": 11.321525, "tags": {"aerialway": "pylon"}}, {"type": "node", "id": 5420295589, "lat": 46.8575457, "lon": 11.3004253, "tags": {"aerialway": "pylon"}}, {"type": "node", "id": 5420295590, "lat": 46.848167, "lon": 11.3050821, "tags": {"aerialway": "pylon"}}, {"type": "node", "id": 5420295591, "lat": 46.8528816, "lon": 11.3062387, "tags": {"aerialway": "pylon"}}, {"type": "node", "id": 5420295592, "lat": 46.8444651, "lon": 11.3108785, "tags": {"aerialway": "pylon"}}, {"type": "node", "id": 5420295593, "lat": 46.8412065, "lon": 11.301959, "tags": {"aerialway": "pylon"}}, {"type": "node", "id": 5420295594, "lat": 46.8439882, "lon": 11.3025101, "tags": {"aerialway": "pylon"}}, {"type": "node", "id": 5420295596, "lat": 46.8476794, "lon": 11.2920359, "tags": {"aerialway": "pylon"}}, {"type": "node", "id": 5420295597, "lat": 46.8410141, "lon": 11.3019209, "tags": {"aerialway": "pylon"}}, {"type": "node", "id": 5420295598, "lat": 46.8417887, "lon": 11.2846744, "tags": {"aerialway": "pylon"}}, {"type": "node", "id": 5420295599, "lat": 46.8602551, "lon": 11.3015608, "tags": {"aerialway": "pylon"}}, {"type": "node", "id": 5420295600, "lat": 46.8445733, "lon": 11.3218018, "tags": {"aerialway": "pylon"}}, {"type": "node", "id": 5420295601, "lat": 46.8479357, "lon": 11.3215993, "tags": {"aerialway": "pylon"}}, {"type": "node", "id": 5420295602, "lat": 46.8433107, "lon": 11.3023759, "tags": {"aerialway": "pylon"}}, {"type": "node", "id": 5420295603, "lat": 46.8500601, "lon": 11.3214714, "tags": {"aerialway": "pylon"}}, {"type": "node", "id": 5420295604, "lat": 46.8434005, "lon": 11.3117899, "tags": {"aerialway": "pylon"}}, {"type": "node", "id": 5420295605, "lat": 46.8556089, "lon": 11.3069079, "tags": {"aerialway": "pylon"}}, {"type": "node", "id": 5420295606, "lat": 46.8462959, "lon": 11.3029673, "tags": {"aerialway": "pylon"}}, {"type": "node", "id": 5420295607, "lat": 46.8486949, "lon": 11.293305, "tags": {"aerialway": "pylon"}}, {"type": "node", "id": 5420295608, "lat": 46.8477756, "lon": 11.3032604, "tags": {"aerialway": "pylon"}}, {"type": "node", "id": 5420295609, "lat": 46.8631111, "lon": 11.3060479, "tags": {"aerialway": "pylon"}}, {"type": "node", "id": 5420295610, "lat": 46.8447228, "lon": 11.288341, "tags": {"aerialway": "pylon"}}, {"type": "node", "id": 5420295611, "lat": 46.844266, "lon": 11.2877701, "tags": {"aerialway": "pylon"}}, {"type": "node", "id": 5420295612, "lat": 46.8435643, "lon": 11.3218626, "tags": {"aerialway": "pylon"}}, {"type": "node", "id": 5420295613, "lat": 46.8486641, "lon": 11.3215555, "tags": {"aerialway": "pylon"}}, {"type": "node", "id": 5420295614, "lat": 46.8457007, "lon": 11.2895631, "tags": {"aerialway": "pylon"}}, {"type": "node", "id": 5420295616, "lat": 46.8478837, "lon": 11.2922913, "tags": {"aerialway": "pylon"}}, {"type": "node", "id": 5420295617, "lat": 46.8471657, "lon": 11.3031396, "tags": {"aerialway": "pylon"}}, {"type": "node", "id": 5420295618, "lat": 46.8546443, "lon": 11.2992095, "tags": {"aerialway": "pylon"}}, {"type": "node", "id": 5420295619, "lat": 46.8602898, "lon": 11.3031555, "tags": {"aerialway": "pylon"}}, {"type": "node", "id": 5420295620, "lat": 46.8473548, "lon": 11.3084043, "tags": {"aerialway": "pylon"}}, {"type": "node", "id": 5420304221, "lat": 46.8489879, "lon": 11.3052835, "tags": {"aerialway": "pylon"}}, {"type": "node", "id": 5420304222, "lat": 46.848153, "lon": 11.3077208, "tags": {"aerialway": "pylon"}}, {"type": "node", "id": 5420304223, "lat": 46.8454173, "lon": 11.321751, "tags": {"aerialway": "pylon"}}, {"type": "node", "id": 5420304224, "lat": 46.8512857, "lon": 11.3058472, "tags": {"aerialway": "pylon"}}, {"type": "node", "id": 5420304225, "lat": 46.8452064, "lon": 11.3102438, "tags": {"aerialway": "pylon"}}, {"type": "node", "id": 5420304226, "lat": 46.8617434, "lon": 11.3046457, "tags": {"aerialway": "pylon"}}, {"type": "node", "id": 5420304227, "lat": 46.8427456, "lon": 11.2858702, "tags": {"aerialway": "pylon"}}, {"type": "node", "id": 5420304228, "lat": 46.8640194, "lon": 11.3069791, "tags": {"aerialway": "pylon"}}, {"type": "node", "id": 5420304229, "lat": 46.8494911, "lon": 11.2943001, "tags": {"aerialway": "pylon"}}, {"type": "node", "id": 5420304230, "lat": 46.8618156, "lon": 11.3084308, "tags": {"aerialway": "pylon"}}, {"type": "node", "id": 5420304232, "lat": 46.8487907, "lon": 11.3071747, "tags": {"aerialway": "pylon"}}, {"type": "node", "id": 5420304233, "lat": 46.858373, "lon": 11.300772, "tags": {"aerialway": "pylon"}}, {"type": "node", "id": 5420304235, "lat": 46.8532625, "lon": 11.2986305, "tags": {"aerialway": "pylon"}}, {"type": "node", "id": 5420304236, "lat": 46.8444762, "lon": 11.3026067, "tags": {"aerialway": "pylon"}}, {"type": "node", "id": 5420304237, "lat": 46.8543905, "lon": 11.306609, "tags": {"aerialway": "pylon"}}, {"type": "node", "id": 5420304238, "lat": 46.8643181, "lon": 11.3072854, "tags": {"aerialway": "pylon"}}, {"type": "node", "id": 5420304239, "lat": 46.8591447, "lon": 11.3010954, "tags": {"aerialway": "pylon"}}, {"type": "node", "id": 5420304240, "lat": 46.8462353, "lon": 11.3217017, "tags": {"aerialway": "pylon"}}, {"type": "node", "id": 5420304241, "lat": 46.8482781, "lon": 11.2965419, "tags": {"aerialway": "pylon"}}, {"type": "node", "id": 5420304242, "lat": 46.852253, "lon": 11.2982074, "tags": {"aerialway": "pylon"}}, {"type": "node", "id": 5420304243, "lat": 46.8427001, "lon": 11.3219147, "tags": {"aerialway": "pylon"}}, {"type": "node", "id": 5420304244, "lat": 46.8421738, "lon": 11.3128402, "tags": {"aerialway": "pylon"}}, {"type": "node", "id": 5420304245, "lat": 46.8568047, "lon": 11.3072013, "tags": {"aerialway": "pylon"}}, {"type": "node", "id": 5420304246, "lat": 46.8414061, "lon": 11.3134974, "tags": {"aerialway": "pylon"}}, {"type": "node", "id": 5420304247, "lat": 46.8634111, "lon": 11.3088223, "tags": {"aerialway": "pylon"}}, {"type": "node", "id": 5420304248, "lat": 46.8433233, "lon": 11.2865921, "tags": {"aerialway": "pylon"}}, {"type": "node", "id": 5420304249, "lat": 46.8468781, "lon": 11.2910344, "tags": {"aerialway": "pylon"}}, {"type": "node", "id": 5420304250, "lat": 46.8405212, "lon": 11.314255, "tags": {"aerialway": "pylon"}}, {"type": "node", "id": 5420304251, "lat": 46.845285, "lon": 11.302767, "tags": {"aerialway": "pylon"}}, {"type": "node", "id": 5420304252, "lat": 46.847092, "lon": 11.3216501, "tags": {"aerialway": "pylon"}}, {"type": "node", "id": 5420304253, "lat": 46.8465169, "lon": 11.3091217, "tags": {"aerialway": "pylon"}}, {"type": "node", "id": 5420304254, "lat": 46.8461466, "lon": 11.2956489, "tags": {"aerialway": "pylon"}}, {"type": "node", "id": 5536465469, "lat": 46.8901623, "lon": 11.0717021, "tags": {"aerialway": "pylon", "source": "Bing Maps"}}, {"type": "node", "id": 5860442248, "lat": 46.9043105, "lon": 11.0779201, "tags": {"aerialway": "station", "aerialway:access": "exit", "aerialway:station": "top", "aerialway:summer:access": "both", "name": "Kirchenkarbahn II", "public_transport": "station", "wikidata": "Q62850468", "wikipedia": "de:Kirchenkarbahn II"}}, {"type": "node", "id": 6776201238, "lat": 46.9471994, "lon": 11.3753744, "tags": {"aerialway": "station", "aerialway:access": "entry", "name": "Wastenegg", "public_transport": "station"}}, {"type": "node", "id": 8668800812, "lat": 46.9088061, "lon": 11.0548894, "tags": {"aerialway": "pylon"}}, {"type": "node", "id": 8668800813, "lat": 46.9082831, "lon": 11.0566507, "tags": {"aerialway": "pylon"}}, {"type": "node", "id": 8668800814, "lat": 46.9073866, "lon": 11.0596697, "tags": {"aerialway": "pylon"}}, {"type": "node", "id": 8668800815, "lat": 46.9063905, "lon": 11.0630245, "tags": {"aerialway": "pylon"}}, {"type": "node", "id": 8668800816, "lat": 46.9060128, "lon": 11.0642963, "tags": {"aerialway": "pylon"}}, {"type": "node", "id": 8668834417, "lat": 46.9050756, "lon": 11.0674524, "tags": {"aerialway": "pylon"}}, {"type": "node", "id": 8668834418, "lat": 46.9044585, "lon": 11.0695304, "tags": {"aerialway": "pylon"}}, {"type": "node", "id": 8668834419, "lat": 46.9041081, "lon": 11.0707105, "tags": {"aerialway": "pylon"}}, {"type": "node", "id": 8668834420, "lat": 46.9040094, "lon": 11.0720709, "tags": {"aerialway": "pylon"}}, {"type": "node", "id": 8668834421, "lat": 46.9042797, "lon": 11.0773207, "tags": {"aerialway": "pylon"}}, {"type": "node", "id": 8668834422, "lat": 46.904291, "lon": 11.0775403, "tags": {"aerialway": "pylon"}}, {"type": "node", "id": 8668834423, "lat": 46.8687739, "lon": 11.0267578, "tags": {"aerialway": "pylon"}}, {"type": "node", "id": 8668834424, "lat": 46.8660353, "lon": 11.0254961, "tags": {"aerialway": "pylon"}}, {"type": "node", "id": 8668834425, "lat": 46.8648075, "lon": 11.0249305, "tags": {"aerialway": "pylon"}}, {"type": "node", "id": 8668834426, "lat": 46.8633533, "lon": 11.0242605, "tags": {"aerialway": "pylon"}}, {"type": "node", "id": 8668834427, "lat": 46.861032, "lon": 11.0231912, "tags": {"aerialway": "pylon"}}, {"type": "node", "id": 8710828745, "lat": 46.9175616, "lon": 11.3961017, "tags": {"aerialway": "pylon"}}, {"type": "node", "id": 8710828746, "lat": 46.9162535, "lon": 11.3989721, "tags": {"aerialway": "pylon"}}, {"type": "node", "id": 8710828747, "lat": 46.9169932, "lon": 11.39735, "tags": {"aerialway": "pylon"}}, {"type": "node", "id": 8710828748, "lat": 46.9154138, "lon": 11.4008134, "tags": {"aerialway": "pylon"}}, {"type": "node", "id": 8710828749, "lat": 46.9152142, "lon": 11.4012512, "tags": {"aerialway": "pylon"}}, {"type": "node", "id": 8710828750, "lat": 46.9144199, "lon": 11.4029929, "tags": {"aerialway": "pylon"}}, {"type": "node", "id": 8710828751, "lat": 46.9136769, "lon": 11.404622, "tags": {"aerialway": "pylon"}}, {"type": "node", "id": 8710828752, "lat": 46.9129049, "lon": 11.4063174, "tags": {"aerialway": "pylon"}}, {"type": "node", "id": 8710828753, "lat": 46.9123561, "lon": 11.4075213, "tags": {"aerialway": "pylon"}}, {"type": "node", "id": 8710828754, "lat": 46.9118819, "lon": 11.4085567, "tags": {"aerialway": "pylon"}}, {"type": "node", "id": 8710828755, "lat": 46.9112652, "lon": 11.4099101, "tags": {"aerialway": "pylon"}}, {"type": "node", "id": 8721161735, "lat": 46.7916039, "lon": 11.0990864, "tags": {"aerialway": "pylon"}}, {"type": "node", "id": 8721161736, "lat": 46.7912764, "lon": 11.0992408, "tags": {"aerialway": "pylon"}}, {"type": "node", "id": 8721161737, "lat": 46.7902851, "lon": 11.0998276, "tags": {"aerialway": "pylon"}}, {"type": "node", "id": 8721161738, "lat": 46.7892234, "lon": 11.1004054, "tags": {"aerialway": "pylon"}}, {"type": "node", "id": 8721161739, "lat": 46.7880477, "lon": 11.1010452, "tags": {"aerialway": "pylon"}}, {"type": "node", "id": 8721161740, "lat": 46.7867573, "lon": 11.1017474, "tags": {"aerialway": "pylon"}}, {"type": "node", "id": 8721161741, "lat": 46.7856794, "lon": 11.102334, "tags": {"aerialway": "pylon"}}, {"type": "node", "id": 8721161742, "lat": 46.7846232, "lon": 11.1029087, "tags": {"aerialway": "pylon"}}, {"type": "node", "id": 8721161743, "lat": 46.7839592, "lon": 11.10327, "tags": {"aerialway": "pylon"}}, {"type": "node", "id": 8721161744, "lat": 46.7832005, "lon": 11.1036828, "tags": {"aerialway": "pylon"}}, {"type": "node", "id": 8721161745, "lat": 46.7821153, "lon": 11.1042734, "tags": {"aerialway": "pylon"}}, {"type": "node", "id": 8721161746, "lat": 46.7808945, "lon": 11.1049376, "tags": {"aerialway": "pylon"}}, {"type": "node", "id": 8721161747, "lat": 46.7800232, "lon": 11.1054117, "tags": {"aerialway": "pylon"}}, {"type": "node", "id": 8721161748, "lat": 46.779969, "lon": 11.1054412, "tags": {"aerialway": "pylon"}}, {"type": "node", "id": 8895877682, "lat": 46.9408149, "lon": 11.3747374, "tags": {"aerialway": "pylon"}}, {"type": "node", "id": 8895877683, "lat": 46.9423394, "lon": 11.3767098, "tags": {"aerialway": "pylon"}}, {"type": "node", "id": 8895877684, "lat": 46.9441952, "lon": 11.3791102, "tags": {"aerialway": "pylon"}}, {"type": "node", "id": 8895877687, "lat": 46.9452195, "lon": 11.3804234, "tags": {"aerialway": "pylon"}}, {"type": "node", "id": 8895877688, "lat": 46.9462633, "lon": 11.3817717, "tags": {"aerialway": "pylon"}}, {"type": "node", "id": 8895877689, "lat": 46.9471609, "lon": 11.3829499, "tags": {"aerialway": "pylon"}}, {"type": "node", "id": 8895877690, "lat": 46.948802, "lon": 11.3850349, "tags": {"aerialway": "pylon"}}, {"type": "node", "id": 8895877693, "lat": 46.9502164, "lon": 11.3868562, "tags": {"aerialway": "pylon"}}, {"type": "node", "id": 8895877694, "lat": 46.9509917, "lon": 11.3878508, "tags": {"aerialway": "pylon"}}, {"type": "node", "id": 8916479883, "lat": 46.7797297, "lon": 11.1055714, "tags": {"aerialway": "station", "ele": "2502", "name": "Karjoch Express"}}, {"type": "node", "id": 9103071522, "lat": 46.8862219, "lon": 11.0769576}, {"type": "node", "id": 9103071602, "lat": 46.8991236, "lon": 11.0521252}, {"type": "node", "id": 9469237259, "lat": 46.9465379, "lon": 11.3748128, "tags": {"aerialway": "pylon"}}, {"type": "node", "id": 9469237260, "lat": 46.9455091, "lon": 11.3739393, "tags": {"aerialway": "pylon"}}, {"type": "node", "id": 9469237261, "lat": 46.9443763, "lon": 11.3729514, "tags": {"aerialway": "pylon"}}, {"type": "node", "id": 9469237262, "lat": 46.9431153, "lon": 11.3719069, "tags": {"aerialway": "pylon"}}, {"type": "node", "id": 9469237263, "lat": 46.9415827, "lon": 11.3706058, "tags": {"aerialway": "pylon"}}, {"type": "node", "id": 9469237264, "lat": 46.9399596, "lon": 11.3692279, "tags": {"aerialway": "pylon"}}, {"type": "node", "id": 9469237265, "lat": 46.9384531, "lon": 11.367949, "tags": {"aerialway": "pylon"}}, {"type": "node", "id": 9469237266, "lat": 46.9368935, "lon": 11.366625, "tags": {"aerialway": "pylon"}}, {"type": "node", "id": 9469237267, "lat": 46.9361851, "lon": 11.3660237, "tags": {"aerialway": "pylon"}}, {"type": "node", "id": 10591523233, "lat": 46.8589894, "lon": 11.0439529, "tags": {"aerialway": "station", "aerialway:access": "exit", "name": "Ro\u00dfkarbahn", "public_transport": "station"}}, {"type": "node", "id": 10646574291, "lat": 46.9462029, "lon": 11.3816936, "tags": {"aerialway": "pylon"}}, {"type": "node", "id": 10646574292, "lat": 46.9457154, "lon": 11.3810639, "tags": {"aerialway": "pylon"}}, {"type": "node", "id": 10646574293, "lat": 46.9457796, "lon": 11.3811469, "tags": {"aerialway": "pylon"}}, {"type": "node", "id": 10646574294, "lat": 46.9458305, "lon": 11.3812126, "tags": {"aerialway": "pylon"}}, {"type": "node", "id": 10646574295, "lat": 46.9495746, "lon": 11.3860298, "tags": {"aerialway": "pylon"}}, {"type": "node", "id": 10815842554, "lat": 46.8692944, "lon": 11.0272506, "tags": {"aerialway": "pylon"}}, {"type": "node", "id": 10815842555, "lat": 46.8693274, "lon": 11.0271956, "tags": {"aerialway": "pylon"}}, {"type": "node", "id": 12077156614, "lat": 46.8494936, "lon": 11.028548}, {"type": "node", "id": 12160592173, "lat": 46.9127079, "lon": 11.3980798, "tags": {"aerialway": "station", "aerialway:access": "both", "aerialway:summer:access": "both", "name": "Rosskopf", "public_transport": "station"}}, {"type": "node", "id": 12498280846, "lat": 46.8773892, "lon": 11.0460951, "tags": {"aerialway": "pylon"}}, {"type": "node", "id": 12498280847, "lat": 46.8953832, "lon": 11.0586462, "tags": {"aerialway": "pylon"}}, {"type": "node", "id": 12840745894, "lat": 46.9176346, "lon": 11.3959417, "tags": {"aerialway": "pylon"}}, {"type": "way", "id": 22789138, "nodes": [244894316, 5420304247, 5420304230, 244894317, 244894318, 5420304245, 5420295605, 5420304237, 5420295591, 5420304224, 244894319, 5420304221, 5420295590, 244894320], "tags": {"aerialway": "gondola", "aerialway:bubble": "no", "aerialway:capacity": "2880", "aerialway:heating": "no", "aerialway:occupancy": "8", "name": "Ratschings-Jaufen - Racines-Giovo", "name:de": "Ratschings-Jaufen", "name:it": "Racines-Giovo", "oneway": "no"}}, {"type": "way", "id": 22789141, "nodes": [244894329, 5420295599, 5420304239, 5420304233, 5420295589, 244894330, 5420295618, 5420304235, 5420304242, 244894331, 5420295581, 5420295582, 5420304241, 5420295585, 5420304254, 244894332], "tags": {"aerialway": "chair_lift", "aerialway:bubble": "yes", "aerialway:capacity": "1800", "aerialway:heating": "no", "aerialway:occupancy": "4", "name": "Wasserfalleralm"}}, {"type": "way", "id": 22789147, "nodes": [244894357, 5420304229, 5420295607, 5420295616, 5420295596, 5420304249, 5420295586, 5420295614, 5420295610, 5420295611, 5420304248, 5420304227, 5420295598, 244894359], "tags": {"aerialway": "chair_lift", "aerialway:bubble": "yes", "aerialway:capacity": "2200", "aerialway:heating": "no", "aerialway:occupancy": "6", "name": "Saxner", "oneway": "yes"}}, {"type": "way", "id": 22789152, "nodes": [244894379, 5420295603, 5420295588, 5420295613, 5420295601, 5420304252, 5420304240, 5420304223, 5420295600, 5420295612, 5420304243, 244894381], "tags": {"aerialway": "chair_lift", "aerialway:bubble": "yes", "aerialway:capacity": "2400", "aerialway:heating": "no", "aerialway:occupancy": "4", "name": "Kalcher Alm - Malga Calice", "name:de": "Kalcher Alm", "name:it": "Malga Calice", "oneway": "yes", "source": "https://www.sentres.com/it/andare-in-malga/malga-calice"}}, {"type": "way", "id": 22789154, "nodes": [244894383, 5420304232, 5420304222, 5420295620, 5420304253, 5420304225, 5420295592, 5420295604, 5420295584, 5420304244, 5420304246, 5420304250, 244894385], "tags": {"aerialway": "chair_lift", "aerialway:bubble": "yes", "aerialway:capacity": "2400", "aerialway:heating": "no", "aerialway:occupancy": "6", "name": "Rinneralm - Malga Rinner", "name:de": "Rinneralm", "name:it": "Malga Rinner", "oneway": "yes"}}, {"type": "way", "id": 22789157, "nodes": [244894394, 5420295608, 5420295617, 5420295606, 5420304251, 5420304236, 5420295594, 5420295602, 5420295587, 5420295593, 5420295597, 244898331], "tags": {"aerialway": "chair_lift", "aerialway:bubble": "yes", "aerialway:capacity": "2800", "aerialway:heating": "no", "aerialway:occupancy": "8", "name": "Enzian"}}, {"type": "way", "id": 23431381, "nodes": [253776121, 1071613852, 253776122, 1066292757, 12498280846, 253776123, 253776124, 253776125, 253776126, 1066292545, 1066293188, 253776128], "tags": {"aerialway": "gondola", "aerialway:occupancy": "8", "name": "Top-Express Obergurgl-Hochgurgl", "oneway": "no"}}, {"type": "way", "id": 23431382, "nodes": [253776129, 253776130, 1618194641, 1066292890, 1066292759, 253776131, 1066293135, 253776132, 253776133, 1066293052, 253776134, 5536465469, 1066293439, 253776135, 1066293236, 9103071522, 1066292694, 1071640770, 253776137], "tags": {"aerialway": "chair_lift", "aerialway:bubble": "yes", "aerialway:heating": "no", "aerialway:occupancy": "4", "name": "Top Wurmkoglbahn I", "oneway": "yes"}}, {"type": "way", "id": 23431383, "nodes": [253776138, 1071640995, 1071640824, 1071641147, 1071640928, 1071641047, 253776141, 1071640829, 253776143, 253776144], "tags": {"aerialway": "chair_lift", "aerialway:bubble": "yes", "aerialway:heating": "no", "aerialway:occupancy": "4", "bicycle": "yes", "layer": "1", "name": "Top Wurmkoglbahn II", "oneway": "no"}}, {"type": "way", "id": 23431384, "nodes": [253776145, 1618152016, 1071640838, 1066293457, 253776146, 1066292818, 253776147, 1066292995, 253776148, 1066292936, 253776149, 253776150, 1066292519, 253776151], "tags": {"aerialway": "gondola", "aerialway:occupancy": "8", "name": "Top Schermer 3000", "oneway": "yes"}}, {"type": "way", "id": 23431385, "nodes": [253776152, 1066292783, 1066293285, 1066292926, 1066292883, 253776154, 1071641070, 1071640785, 1066292845, 1103629491], "tags": {"aerialway": "chair_lift", "aerialway:occupancy": "6", "name": "Gro\u00dfe Karbahn"}}, {"type": "way", "id": 23431387, "nodes": [1066293157, 1071613624, 1066293519, 1066293118, 1066293082, 1066293460, 1066293393, 1066292822, 1066292633, 253776167, 253776168, 1066292997, 1066292941, 253776169, 253776170, 253776171, 1066293303, 253776172], "tags": {"aerialway": "gondola", "aerialway:bubble": "no", "aerialway:heating": "no", "aerialway:occupancy": "6", "lit": "yes", "name": "Festkoglbahn", "oneway": "no"}}, {"type": "way", "id": 23431389, "nodes": [253776177, 10815842555, 10815842554, 1066293396, 1066293306, 1066292762, 1066293228, 1066292565, 253776179, 1066292875, 1066293166, 253776180], "tags": {"aerialway": "gondola", "aerialway:bubble": "no", "aerialway:heating": "no", "aerialway:occupancy": "10", "name": "Ro\u00dfkarbahn", "oneway": "no"}}, {"type": "way", "id": 23431390, "nodes": [253776186, 1066293185, 1066293022, 253776187, 1066293420, 1066293331, 1066292774, 1066292595, 1066292962, 1066293532, 253776189], "tags": {"aerialway": "chair_lift", "aerialway:bubble": "yes", "aerialway:heating": "no", "aerialway:occupancy": "4", "name": "Plattachbahn", "oneway": "yes"}}, {"type": "way", "id": 23431391, "nodes": [253776204, 8668834427, 8668834426, 8668834425, 8668834424, 8668834423, 253776196], "tags": {"aerialway": "gondola", "aerialway:duration": "5", "aerialway:heating": "no", "aerialway:occupancy": "8", "bicycle": "yes", "name": "Hohe Mut Bahn I", "oneway": "no", "wikidata": "Q97327948"}}, {"type": "way", "id": 23431392, "nodes": [253776211, 1071613878, 1071614093, 1071614173, 1071613653, 3545826061], "tags": {"aerialway": "chair_lift", "aerialway:bubble": "no", "aerialway:heating": "no", "aerialway:occupancy": "4", "name": "Bruggenbodenlift"}}, {"type": "way", "id": 23431393, "nodes": [1071613743, 1071613608, 1071613912, 1071614104, 1071613978, 1071614075, 253776218], "tags": {"aerialway": "chair_lift", "aerialway:bubble": "yes", "aerialway:duration": "3:10", "aerialway:heating": "no", "aerialway:occupancy": "6", "name": "Steinmannbahn"}}, {"type": "way", "id": 26950678, "nodes": [295318451, 1083602580, 1083602611, 3925544941, 3925544925, 3925544935, 3925544912, 3925544944, 4973565015, 1554120762], "tags": {"aerialway": "chair_lift", "aerialway:bubble": "no", "aerialway:duration": "7", "aerialway:heating": "no", "aerialway:occupancy": "2", "name": "Wildspitze", "oneway": "no"}}, {"type": "way", "id": 28523287, "nodes": [313310535, 3226930339, 3226930338, 3226930337, 3226930336, 3226930335, 3226930334, 3226930333, 3226930332, 3226930331, 313310536], "tags": {"aerialway": "gondola", "aerialway:bicycle": "no", "aerialway:bubble": "no", "aerialway:capacity": "2800", "aerialway:duration": "5.67", "aerialway:heating": "no", "aerialway:occupancy": "8", "name": "Tiefenbachbahn", "oneway": "no", "ref": "E66", "wikidata": "Q130284844"}}, {"type": "way", "id": 28523289, "nodes": [313310539, 3226931300, 3226931301, 3226931302, 3226931303, 3226931304, 3226931305, 3226931306, 313310540], "tags": {"aerialway": "chair_lift", "aerialway:bubble": "yes", "aerialway:capacity": "3000", "aerialway:duration": "3", "aerialway:heating": "no", "aerialway:occupancy": "6", "name": "Seiterkar", "oneway": "yes", "ref": "E65"}}, {"type": "way", "id": 30752537, "nodes": [340106300, 1618130726, 1618130747, 1079431722, 1079431769, 1618130754, 1618130767, 340106299], "tags": {"aerialway": "gondola", "aerialway:heating": "no", "aerialway:occupancy": "8", "bicycle": "yes", "name": "Hochgurglbahn I", "oneway": "no"}}, {"type": "way", "id": 30752538, "nodes": [340106299, 9103071602, 1066293487, 1066293274, 1066292720, 12498280847, 1066293175, 1066292585, 1066293401, 1066292823, 1066292765, 1066293139, 1066292948, 1066293312, 340106298], "tags": {"aerialway": "gondola", "aerialway:heating": "no", "aerialway:occupancy": "8", "bicycle": "yes", "name": "Hochgurglbahn II", "oneway": "no"}}, {"type": "way", "id": 30752941, "nodes": [253776204, 1086985592, 1086985575, 1086985568, 1086985595, 1086985599, 1086985557, 1071614043, 1086985597, 1086985612, 1086985609, 1086985615, 1086985590, 12077156614, 1086985561, 253776210], "tags": {"aerialway": "gondola", "aerialway:duration": "6", "aerialway:heating": "no", "aerialway:occupancy": "8", "bicycle": "yes", "name": "Hohe Mut Bahn II", "oneway": "no", "wikidata": "Q97327948"}}, {"type": "way", "id": 30816316, "nodes": [341999459, 2458659523, 2458659533, 2458659541, 2458659552, 5065053633, 5065053632, 5065053631, 5065053630, 5065053629, 5065053628, 5065053627, 5065053626, 5065053625, 3239032538], "tags": {"aerialway": "chair_lift", "aerialway:bubble": "yes", "aerialway:duration": "5.33", "aerialway:heating": "no", "aerialway:occupancy": "4", "name": "Heidebahn", "oneway": "yes", "ref": "A13"}}, {"type": "way", "id": 43133267, "nodes": [540378278, 8895877694, 8895877693, 10646574295, 8895877690, 8895877689, 8895877688, 10646574291, 10646574294, 10646574293, 10646574292, 8895877687, 8895877684, 8895877683, 8895877682, 540378274], "tags": {"aerialway": "gondola", "aerialway:capacity": "2000", "aerialway:duration": "5", "aerialway:occupancy": "10", "name": "Ladurns", "ref": "A"}}, {"type": "way", "id": 43133268, "nodes": [6776201238, 9469237259, 9469237260, 9469237261, 9469237262, 9469237263, 9469237264, 9469237265, 9469237266, 9469237267, 4109928652], "tags": {"aerialway": "chair_lift", "aerialway:bubble": "yes", "aerialway:capacity": "2600", "aerialway:duration": "5", "aerialway:heating": "no", "aerialway:occupancy": "6", "name": "Wastenegg", "ref": "B"}}, {"type": "way", "id": 53672480, "nodes": [677810074, 8721161735, 8721161736, 8721161737, 8721161738, 8721161739, 8721161740, 8721161741, 8721161742, 8721161743, 8721161744, 8721161745, 8721161746, 8721161747, 8721161748, 8916479883], "tags": {"aerialway": "chair_lift", "aerialway:bubble": "yes", "aerialway:occupancy": "4", "name": "Karjoch Express"}}, {"type": "way", "id": 59465925, "nodes": [737415765, 8710828755, 8710828754, 8710828753, 8710828752, 8710828751, 8710828750, 8710828749, 8710828748, 8710828746, 8710828747, 8710828745, 12840745894, 737414842], "tags": {"aerialway": "chair_lift", "aerialway:bubble": "no", "aerialway:heating": "no", "aerialway:occupancy": "4", "layer": "1", "name": "Stock", "source": "foreign trace from OSM"}}, {"type": "way", "id": 91758762, "nodes": [253776189, 3836944824, 1066292918, 253776191, 1066293158, 1066292802, 1066293093, 1066293488, 1071614013, 253776195], "tags": {"aerialway": "chair_lift", "aerialway:bubble": "yes", "aerialway:heating": "no", "aerialway:occupancy": "4", "name": "Plattachbahn", "oneway": "yes"}}, {"type": "way", "id": 91758763, "nodes": [253776180, 1066292655, 1066293535, 253776181, 1066293210, 1066293057, 1066292850, 1066292551, 10591523233], "tags": {"aerialway": "gondola", "aerialway:bubble": "no", "aerialway:heating": "no", "aerialway:occupancy": "10", "name": "Ro\u00dfkarbahn", "oneway": "no"}}, {"type": "way", "id": 140592069, "nodes": [3229720256, 669878657, 669878652, 313310543], "tags": {"aerialway": "gondola", "aerialway:bicycle": "no", "aerialway:bubble": "no", "aerialway:capacity": "2800", "aerialway:duration": "2.67", "aerialway:heating": "no", "aerialway:occupancy": "8", "name": "Schwarze Schneid II", "oneway": "no", "ref": "E62"}}, {"type": "way", "id": 154159139, "nodes": [3545808258, 8668800812, 8668800813, 8668800814, 8668800815, 8668800816, 8668834417, 8668834418, 8668834419, 1667413113], "tags": {"aerialway": "gondola", "aerialway:capacity": "2400", "aerialway:duration": "4,25", "aerialway:heating": "yes", "aerialway:occupancy": "10", "name": "Kirchenkarbahn I", "oneway": "yes", "source": "gpx", "wikidata": "Q62850457", "wikipedia": "de:Kirchenkarbahn I"}}, {"type": "way", "id": 170481021, "nodes": [447031896, 4823572428, 4823572436, 4823572426, 4823572429, 4823572427, 4823572432, 4823572438, 4823568020, 4823568017, 4823572437, 4823572422, 4823572431, 4823572433, 4823568019, 12160592173], "tags": {"aerialway": "gondola", "aerialway:capacity": "2400", "aerialway:duration": "8", "aerialway:heating": "no", "aerialway:occupancy": "10", "bicycle": "yes", "layer": "1", "name": "Rosskopf", "oneway": "no"}}, {"type": "way", "id": 207590650, "nodes": [2178445703, 5420304238, 5420304228, 5420295609, 5420304226, 5420295583, 5420295619, 244894345], "tags": {"aerialway": "chair_lift", "aerialway:bubble": "no", "aerialway:heating": "no", "aerialway:occupancy": "2", "name": "Blosegg - Maso Blasegger", "name:de": "Blosegg", "name:it": "Maso Blasegger"}}, {"type": "way", "id": 620264342, "nodes": [1667413113, 8668834420, 8668834421, 8668834422, 5860442248], "tags": {"aerialway": "gondola", "aerialway:heating": "yes", "aerialway:occupancy": "10", "name": "Kirchenkarbahn II", "oneway": "yes", "wikidata": "Q62850468", "wikipedia": "de:Kirchenkarbahn II"}}]}